bigbluebutton_api_python/__init__.py
bigbluebutton_api_python/bigbluebutton.py
bigbluebutton_api_python/core/__init__.py
bigbluebutton_api_python/core/apimethod.py
bigbluebutton_api_python/core/attendance.py
bigbluebutton_api_python/core/attendee.py
bigbluebutton_api_python/core/meeting.py
bigbluebutton_api_python/core/meetinginfo.py
bigbluebutton_api_python/core/metaData.py
bigbluebutton_api_python/core/record.py
bigbluebutton_api_python/exception/__init__.py
bigbluebutton_api_python/exception/bbbexception.py
bigbluebutton_api_python/parameters/__init__.py
bigbluebutton_api_python/parameters/bbbmodule.py
bigbluebutton_api_python/responses/__init__.py
bigbluebutton_api_python/responses/apiversion.py
bigbluebutton_api_python/responses/base.py
bigbluebutton_api_python/responses/createmeeting.py
bigbluebutton_api_python/responses/deleterecordings.py
bigbluebutton_api_python/responses/endmeeting.py
bigbluebutton_api_python/responses/getattendance.py
bigbluebutton_api_python/responses/getmeetinginfo.py
bigbluebutton_api_python/responses/getmeetings.py
bigbluebutton_api_python/responses/getrecordings.py
bigbluebutton_api_python/responses/ismeetingrunning.py
bigbluebutton_api_python/responses/publishrecordings.py
bigbluebutton_api_python/responses/setconfigxml.py
bigbluebutton_api_python/responses/updaterecordings.py
bigbluebutton_api_python/util/__init__.py
bigbluebutton_api_python/util/urlbuilder.py
bigbluebutton_api_python_medad-0.0.17.dist-info/LICENSE
bigbluebutton_api_python_medad-0.0.17.dist-info/METADATA
bigbluebutton_api_python_medad-0.0.17.dist-info/WHEEL
bigbluebutton_api_python_medad-0.0.17.dist-info/top_level.txt
bigbluebutton_api_python_medad-0.0.17.dist-info/RECORD
